diha/__init__.py
diha/builders.py
diha/calc.py
diha/commands.py
diha/components.py
diha/fibers.py
diha/geometry.py
diha/materials.py
diha/sections.py
diha/utils.py
diha-0.1.0.dist-info/LICENSE
diha-0.1.0.dist-info/METADATA
diha-0.1.0.dist-info/WHEEL
diha-0.1.0.dist-info/entry_points.txt
diha-0.1.0.dist-info/top_level.txt
diha-0.1.0.dist-info/RECORD
