Metadata-Version: 2.2
Name: diha
Version: 0.1.0
Summary: Diagramas de Interacción para elementos de barra Hormigón Armado
Author-email: "Pablo E. Andino" <pabloe.andino@gmail.com>
Project-URL: Homepage, https://github.com/pavloae/diha
Project-URL: Bug Tracker, https://github.com/pavloae/diha/issues
Classifier: Programming Language :: Python :: 3
Classifier: License :: OSI Approved :: MIT License
Classifier: Operating System :: OS Independent
Requires-Python: >=3.7
License-File: LICENSE
Requires-Dist: matplotlib==3.10.0
Requires-Dist: numpy==2.2.2
Provides-Extra: cli
Requires-Dist: click==8.1.8; extra == "cli"
